.gitattributes
.gitignore
CODENAME
COPYRIGHT.txt
README.md
VERSION
make.sh
setup.py
setup.py.in
bin/binfmt-helper
bin/fchroot
bin/magic-reader
bin/wrapper-builder
fchroot/__init__.py
fchroot/binfmt.py
fchroot/common.py
fchroot/version.py
fchroot.egg-info/PKG-INFO
fchroot.egg-info/SOURCES.txt
fchroot.egg-info/dependency_links.txt
fchroot.egg-info/top_level.txt
man/fchroot.1.rst.in