Metadata-Version: 2.1
Name: fchroot
Version: 1.0.1
Summary: Funtoo franken-chroot tool.
Home-page: https://code.funtoo.org/bitbucket/users/drobbins/repos/fchroot/browse
Author: Daniel Robbins
Author-email: drobbins@funtoo.org
Classifier: Programming Language :: Python :: 3
Classifier: License :: OSI Approved :: Apache Software License
Classifier: Operating System :: POSIX :: Linux
Requires-Python: >=3.7
